supereasyai/__init__.py
supereasyai/ai.py
supereasyai/messages.py
supereasyai/bases/__init__.py
supereasyai/bases/groq_base.py
supereasyai/bases/open_ai_base.py
supereasyai-1.0.5.dist-info/licenses/LICENSE
supereasyai-1.0.5.dist-info/METADATA
supereasyai-1.0.5.dist-info/WHEEL
supereasyai-1.0.5.dist-info/top_level.txt
supereasyai-1.0.5.dist-info/RECORD
