Metadata-Version: 2.4
Name: supereasyai
Version: 1.0.5
Summary: A super easy AI LLM library.
Author: Dominic Coletti
License-Expression: Apache-2.0
Project-URL: Homepage, https://github.com/DominicDJC/supereasyai
Project-URL: Changelog, https://github.com/DominicDJC/supereasyai/releases
Project-URL: Issues, https://github.com/DominicDJC/supereasyai/issues
Project-URL: CI, https://github.com/DominicDJC/supereasyai/actions
Requires-Python: >=3.8
License-File: LICENSE
Requires-Dist: doms-json
Requires-Dist: openai
Requires-Dist: groq
Provides-Extra: test
Requires-Dist: pytest; extra == "test"
Requires-Dist: python-dotenv; extra == "test"
Dynamic: license-file
